nr/stream/__init__.py
nr/stream/_notset.py
nr/stream/_optional.py
nr/stream/_refreshable.py
nr/stream/_stream.py
nr/stream/_supplier.py
nr/stream/py.typed
nr_stream-1.1.4.dist-info/LICENSE
nr_stream-1.1.4.dist-info/METADATA
nr_stream-1.1.4.dist-info/WHEEL
nr_stream-1.1.4.dist-info/RECORD
